SimPEG.py
mira_simpeg-0.23.0.2.dist-info/licenses/AUTHORS.rst
mira_simpeg-0.23.0.2.dist-info/licenses/LICENSE
simpeg/__init__.py
simpeg/data.py
simpeg/data_misfit.py
simpeg/fields.py
simpeg/inverse_problem.py
simpeg/inversion.py
simpeg/maps.py
simpeg/models.py
simpeg/objective_function.py
simpeg/optimization.py
simpeg/props.py
simpeg/simulation.py
simpeg/survey.py
simpeg/version.py
simpeg/base/__init__.py
simpeg/base/pde_simulation.py
simpeg/dask/__init__.py
simpeg/dask/inverse_problem.py
simpeg/dask/objective_function.py
simpeg/dask/simulation.py
simpeg/dask/utils.py
simpeg/dask/electromagnetics/__init__.py
simpeg/dask/electromagnetics/frequency_domain/__init__.py
simpeg/dask/electromagnetics/frequency_domain/simulation.py
simpeg/dask/electromagnetics/static/__init__.py
simpeg/dask/electromagnetics/static/induced_polarization/__init__.py
simpeg/dask/electromagnetics/static/induced_polarization/simulation.py
simpeg/dask/electromagnetics/static/induced_polarization/simulation_2d.py
simpeg/dask/electromagnetics/static/resistivity/__init__.py
simpeg/dask/electromagnetics/static/resistivity/simulation.py
simpeg/dask/electromagnetics/static/resistivity/simulation_2d.py
simpeg/dask/electromagnetics/time_domain/__init__.py
simpeg/dask/electromagnetics/time_domain/simulation.py
simpeg/dask/electromagnetics/time_domain/simulation_1d.py
simpeg/dask/potential_fields/__init__.py
simpeg/dask/potential_fields/base.py
simpeg/dask/potential_fields/gravity/__init__.py
simpeg/dask/potential_fields/gravity/simulation.py
simpeg/dask/potential_fields/magnetics/__init__.py
simpeg/dask/potential_fields/magnetics/simulation.py
simpeg/directives/__init__.py
simpeg/directives/_regularization.py
simpeg/directives/_save_geoh5.py
simpeg/directives/_vector_models.py
simpeg/directives/directives.py
simpeg/directives/pgi_directives.py
simpeg/directives/sim_directives.py
simpeg/electromagnetics/__init__.py
simpeg/electromagnetics/base.py
simpeg/electromagnetics/base_1d.py
simpeg/electromagnetics/analytics/DC.py
simpeg/electromagnetics/analytics/FDEM.py
mira_simpeg-0.23.0.2.dist-info/METADATA
mira_simpeg-0.23.0.2.dist-info/WHEEL
mira_simpeg-0.23.0.2.dist-info/top_level.txt
mira_simpeg-0.23.0.2.dist-info/RECORD
