Metadata-Version: 2.4
Name: mira-simpeg
Version: 0.23.0.2
Summary: Mira Geoscience fork of SimPEG: Simulation and Parameter Estimation in Geophysics
Author-email: SimPEG developers <rowanc1@gmail.com>, Dominique Fournier <dominiquef@mirageoscience.com>
License: The MIT License (MIT)
Project-URL: Homepage, https://simpeg.xyz
Project-URL: Documentation, https://docs.simpeg.xyz
Project-URL: Repository, http://github.com/MiraGeoscience/simpeg
Keywords: geophysics,inverse problem
Classifier: Development Status :: 4 - Beta
Classifier: Intended Audience :: Developers
Classifier: Intended Audience :: Science/Research
Classifier: License :: OSI Approved :: MIT License
Classifier: Programming Language :: Python
Classifier: Topic :: Scientific/Engineering
Classifier: Topic :: Scientific/Engineering :: Mathematics
Classifier: Topic :: Scientific/Engineering :: Physics
Classifier: Topic :: Software Development :: Libraries :: Python Modules
Classifier: Operating System :: Microsoft :: Windows
Classifier: Operating System :: POSIX
Classifier: Operating System :: Unix
Classifier: Operating System :: MacOS
Classifier: Natural Language :: English
Requires-Python: <4.0,>=3.10
License-File: LICENSE
License-File: AUTHORS.rst
Requires-Dist: discretize>=0.11
Requires-Dist: geoana>=0.7.0
Requires-Dist: geoh5py<0.13.dev,>=0.12.0b3
Requires-Dist: libdlf
Requires-Dist: matplotlib
Requires-Dist: numpy>=1.22
Requires-Dist: pymatsolver>=0.3
Requires-Dist: scipy>=1.8
Provides-Extra: dask
Requires-Dist: dask; extra == "dask"
Requires-Dist: zarr; extra == "dask"
Requires-Dist: fsspec>=0.3.3; extra == "dask"
Provides-Extra: choclo
Requires-Dist: choclo>=0.3.0; extra == "choclo"
Provides-Extra: reporting
Requires-Dist: scooby; extra == "reporting"
Provides-Extra: plotting
Requires-Dist: plotly; extra == "plotting"
Provides-Extra: sklearn
Requires-Dist: scikit-learn>=1.2; extra == "sklearn"
Provides-Extra: pandas
Requires-Dist: pandas; extra == "pandas"
Provides-Extra: all
Requires-Dist: simpeg[choclo,dask,pandas,plotting,reporting,sklearn]; extra == "all"
Provides-Extra: style
Requires-Dist: black==24.3.0; extra == "style"
Requires-Dist: flake8==7.0.0; extra == "style"
Requires-Dist: flake8-bugbear==23.12.2; extra == "style"
Requires-Dist: flake8-builtins==2.2.0; extra == "style"
Requires-Dist: flake8-mutable==1.2.0; extra == "style"
Requires-Dist: flake8-rst-docstrings==0.3.0; extra == "style"
Requires-Dist: flake8-docstrings==1.7.0; extra == "style"
Requires-Dist: flake8-pyproject==1.2.3; extra == "style"
Provides-Extra: docs
Requires-Dist: sphinx; extra == "docs"
Requires-Dist: sphinx-gallery>=0.1.13; extra == "docs"
Requires-Dist: sphinxcontrib-apidoc; extra == "docs"
Requires-Dist: pydata-sphinx-theme; extra == "docs"
Requires-Dist: nbsphinx; extra == "docs"
Requires-Dist: empymod>=2.0.0; extra == "docs"
Requires-Dist: numpydoc; extra == "docs"
Requires-Dist: pillow; extra == "docs"
Requires-Dist: sympy; extra == "docs"
Requires-Dist: memory_profiler; extra == "docs"
Requires-Dist: python-kaleido; extra == "docs"
Provides-Extra: tests
Requires-Dist: simpeg[all,docs]; extra == "tests"
Requires-Dist: pytest; extra == "tests"
Requires-Dist: pytest-cov; extra == "tests"
Provides-Extra: dev
Requires-Dist: simpeg[all,docs,style,tests]; extra == "dev"
Dynamic: license-file
